INSTALL.rst
LICENSE
MANIFEST.in
README.rst
requirements.txt
setup.py
src/qturtle/__init__.py
src/qturtle/__main__.py
src/qturtle/colors.py
src/qturtle/kernel.py
src/qturtle/mainwindow.py
src/qturtle/mathutil.py
src/qturtle/mixins.py
src/qturtle/qscieditor.py
src/qturtle/qtconsole.py
src/qturtle/repleditor.py
src/qturtle/turtlescene.py
src/qturtle/turtlewidget.py
src/qturtle/utils.py
src/qturtle.egg-info/PKG-INFO
src/qturtle.egg-info/SOURCES.txt
src/qturtle.egg-info/dependency_links.txt
src/qturtle.egg-info/entry_points.txt
src/qturtle.egg-info/not-zip-safe
src/qturtle.egg-info/requires.txt
src/qturtle.egg-info/top_level.txt
src/qturtle/data/icon.svg
src/qturtle/data/main.ui
src/qturtle/data/qturtle.ts
src/qturtle/data/qturtle_es_BR.qm
src/qturtle/data/qturtle_es_BR.ts
src/qturtle/data/qturtle_ko_KR.qm
src/qturtle/data/qturtle_ko_KR.ts
src/qturtle/data/qturtle_pt_BR.qm
src/qturtle/data/qturtle_pt_BR.ts
src/qturtle/data/turtleart.svg
src/qturtle/data/examples/curva_de_koch.pytg
src/qturtle/data/examples/entrada_e_saida.pytg
src/qturtle/data/examples/estrela.pytg
src/qturtle/data/examples/ladrilhamento_de_penrose.pytg